Metadata-Version: 1.1
Name: coursetemplater
Version: 0.1
Summary: Creates a directory layout for a subject/course file
Home-page: https://github.com/CoolDudde4150/coursetemplater
Author: CoolDudde4150
Author-email: UNKNOWN
License: MIT
Download-URL: https://github.com/CoolDudde4150/coursetemplater/archive/v0.1.tar.gz
Platform: UNKNOWN
